pycounts_bill_mds/__init__.py
pycounts_bill_mds/plotting.py
pycounts_bill_mds/pycounts_bill_mds.py
pycounts_bill_mds-0.1.1.dist-info/LICENSE
pycounts_bill_mds-0.1.1.dist-info/METADATA
pycounts_bill_mds-0.1.1.dist-info/WHEEL
pycounts_bill_mds-0.1.1.dist-info/RECORD
