Metadata-Version: 2.1
Name: pycounts_bill_mds
Version: 0.1.1
Summary: Calculate word counts in a text file!
License: MIT
Author: Bill Wan
Requires-Python: >=3.11
Classifier: License :: OSI Approved :: MIT License
Classifier: Programming Language :: Python :: 3
Classifier: Programming Language :: Python :: 3.11
Classifier: Programming Language :: Python :: 3.12
Requires-Dist: matplotlib (>=3.8.2)
